aaaaaa_deliverymethod.pth
deliverymethod.py
deliverymethod-0.1.dist-info/DESCRIPTION.rst
deliverymethod-0.1.dist-info/LICENSE.txt
deliverymethod-0.1.dist-info/METADATA
deliverymethod-0.1.dist-info/RECORD
deliverymethod-0.1.dist-info/WHEEL
deliverymethod-0.1.dist-info/metadata.json
deliverymethod-0.1.dist-info/top_level.txt
